{
  "generated_at": "2026-04-24T09:15:00.978970+10:00",
  "generated_display": "9:15am AEST \u00b7 24 Apr 2026",
  "weekday": "Friday",
  "jobs_today": [
    {
      "time": "3am",
      "label": "Reports retention (Stu)",
      "status": "ran",
      "detail": "3am cleanup \u00b7 >14d purged"
    },
    {
      "time": "6:30am",
      "label": "Newsletter digest synthesised",
      "status": "ran",
      "detail": "38 newsletters synthesised"
    },
    {
      "time": "7am",
      "label": "Morning brief delivered",
      "status": "ran",
      "detail": "10 sections \u00b7 17 live feeds"
    },
    {
      "time": "7:25am",
      "label": "Diagnostic heartbeat",
      "status": "ran",
      "detail": "all green"
    },
    {
      "time": "10am",
      "label": "Investment scanner",
      "status": "pending",
      "detail": "86 tickers \u00b7 Drive auto-sync"
    },
    {
      "time": "7pm",
      "label": "Edge Bet scanner",
      "status": "pending",
      "detail": "8W 8L \u00b7 bank $47.68"
    }
  ],
  "footer": {
    "active_crons": 7,
    "drive_files_synced": 120,
    "edge_bet_record": "8W 8L",
    "dashboard_last_refresh": "2026-04-20",
    "heartbeat_last": "green"
  }
}